GOUD/PlaneacionAgregada.py
GOUD/ProgramacionProduccion.py
GOUD/Pronosticos.py
GOUD/__init__.py
GOUD-1.0.5.dist-info/LICENSE
GOUD-1.0.5.dist-info/METADATA
GOUD-1.0.5.dist-info/WHEEL
GOUD-1.0.5.dist-info/top_level.txt
GOUD-1.0.5.dist-info/RECORD
