Metadata-Version: 2.1
Name: GOUD
Version: 1.0.5
Summary: Modelos heuristicos o porgrmación lineal de Ingeneria Industrial para Pronosticos, Planeacion Agregada y Plan Maestro de Producción
Home-page: https://github.com/miguelcortes0999/Industrial-Engineering
Author: miguelcortes0999
Author-email: miguelcortes0999@gmail.com
License: GNU General Public License v3.0
License-File: LICENSE
Requires-Dist: pandas
Requires-Dist: pulp
Requires-Dist: numpy
Requires-Dist: gurobipy
Requires-Dist: matplotlib
Requires-Dist: openpyxl
Requires-Dist: networkx
